{
  "verbose": true,
  "plugins": {
    "sauce": {
      "browsers": [{
          "browserName": "microsoftedge",
          "platform": "Windows 10",
          "version": ""
        },
        {
          "browserName": "internet explorer",
          "platform": "Windows 8.1",
          "version": "latest"
        },
        {
          "browserName": "internet explorer",
          "platform": "Windows 8.1",
          "version": "latest-1"
        },
        {
          "browserName": "internet explorer",
          "platform": "Windows 7",
          "version": "latest"
        },
        {
          "browserName": "internet explorer",
          "platform": "Windows 7",
          "version": "latest-1"
        },
        {
          "browserName": "safari",
          "platform": "OS X 10.11",
          "version": "latest"
        },
        {
          "browserName": "firefox",
          "platform": "OS X 10.10",
          "version": ""
        },
        {
          "browserName": "chrome",
          "platform": "OS X 10.10",
          "version": ""
        }]
    },
    "local": {
      "browsers": ["chrome", "firefox"]
    }
  }
}
